{"eval/rouge1": 28.5279, "eval/rouge2": 9.119, "eval/rougeL": 22.3713, "eval/rougeLsum": 26.1264, "eval/gen_len": 39.81, "eval/runtime": 422.4493, "eval/samples_per_second": 0.237, "eval/steps_per_second": 0.237, "eval/block_avg": 21.032403918612886, "train/time_encoder_forward": "0:00:00", "train/time_decoder_forward": "0:06:45", "train/time_key_value_gen": "['0:00:19', '0:00:02']", "train/time_attn": "['0:00:27', '0:00:31']", "train/time_ffn": "0:00:57", "train/time_confidence": "0:01:19", "train/time_exit_key_value_gen": "['0:00:02', '0:00:00']", "train/time_exit_attn": "['0:00:00', '0:00:00']", "train/time_exit_ffn": "0:00:00", "train/time_parallel_key_value_gen": "['0:00:00', '0:00:00']", "train/time_parallel_attn": "['0:00:00', '0:00:00']", "train/time_parallel_ffn": "0:00:00", "train/time_estimate_conf": "0:00:00", "train/time_others": "0:00:05", "train/global_step": 0, "_timestamp": 1716539486.346781, "_runtime": 440.74327993392944, "_step": 0, "_wandb": {"runtime": 440}}